llama_index/tools/measurespace/__init__.py
llama_index/tools/measurespace/base.py
llama_index_tools_measurespace-0.2.1.dist-info/METADATA
llama_index_tools_measurespace-0.2.1.dist-info/WHEEL
llama_index_tools_measurespace-0.2.1.dist-info/licenses/LICENSE
llama_index_tools_measurespace-0.2.1.dist-info/RECORD
