Metadata-Version: 2.4
Name: llama-index-tools-measurespace
Version: 0.2.1
Summary: llama-index tools weather, climate, air quality and geocoding integration
Author-email: Measure Space <support@measurespace.io>
Maintainer: MeasureSpace
License-Expression: MIT
License-File: LICENSE
Requires-Python: >=3.10
Requires-Dist: llama-index-core>=0.12.0
Requires-Dist: measure-space-api>=0.1.0
